{"web":{"client_id":"200954623137-bavqgl56b5bk34orn3g1cb7ocb4bk5d5.apps.googleusercontent.com","project_id":"twohills-1080","auth_uri":"https://accounts.google.com/o/oauth2/auth","token_uri":"https://accounts.google.com/o/oauth2/token","auth_provider_x509_cert_url":"https://www.googleapis.com/oauth2/v1/certs","client_secret":"cRdsxH8984mPai1RW5R_NInd","redirect_uris":["http://localhost/th/sys/valida.php","http://twohills.com.br/sys/valida.php","http://www.twohills.com.br/sys/valida.php","http://localhost/twohills.tv/","http://localhost/twohills.tv/dev/Alpha/valida.php"]}}